sentry_notify_github_issues/__init__.py
sentry_notify_github_issues/plugin.py
sentry_notify_github_issues-1.0.0.dist-info/DESCRIPTION.rst
sentry_notify_github_issues-1.0.0.dist-info/METADATA
sentry_notify_github_issues-1.0.0.dist-info/RECORD
sentry_notify_github_issues-1.0.0.dist-info/WHEEL
sentry_notify_github_issues-1.0.0.dist-info/entry_points.txt
sentry_notify_github_issues-1.0.0.dist-info/metadata.json
sentry_notify_github_issues-1.0.0.dist-info/top_level.txt
