Metadata-Version: 2.0
Name: sentry-notify-github-issues
Version: 1.0.0
Summary: A Sentry notification plugin for GitHub issues.
Home-page: http://github.com/yoshiori/sentry-notify-github-issues
Author: Yoshiori Shoji
Author-email: yoshiori@gmail.com
License: MTI
Platform: UNKNOWN
Classifier: Framework :: Django
Classifier: Intended Audience :: Developers
Classifier: Intended Audience :: System Administrators
Classifier: Operating System :: OS Independent
Classifier: Topic :: Software Development
Requires-Dist: sentry (>=5.0.0)
Provides-Extra: test
Requires-Dist: nose; extra == 'test'
